opencensus/__init__.py
opencensus/ext/__init__.py
opencensus/ext/google_cloud_clientlibs/__init__.py
opencensus/ext/google_cloud_clientlibs/trace.py
opencensus_ext_google_cloud_clientlibs-0.1.3.dist-info/METADATA
opencensus_ext_google_cloud_clientlibs-0.1.3.dist-info/WHEEL
opencensus_ext_google_cloud_clientlibs-0.1.3.dist-info/namespace_packages.txt
opencensus_ext_google_cloud_clientlibs-0.1.3.dist-info/top_level.txt
opencensus_ext_google_cloud_clientlibs-0.1.3.dist-info/RECORD
