Metadata-Version: 2.1
Name: opencensus-ext-google-cloud-clientlibs
Version: 0.1.3
Summary: OpenCensus Google Cloud Client Libraries Integration
Home-page: https://github.com/census-instrumentation/opencensus-python/tree/master/contrib/opencensus-ext-google-cloud-clientlibs
Author: OpenCensus Authors
Author-email: census-developers@googlegroups.com
License: Apache-2.0
Platform: UNKNOWN
Classifier: Intended Audience :: Developers
Classifier: Development Status :: 3 - Alpha
Classifier: Intended Audience :: Developers
Classifier: License :: OSI Approved :: Apache Software License
Classifier: Programming Language :: Python
Classifier: Programming Language :: Python :: 2
Classifier: Programming Language :: Python :: 2.7
Classifier: Programming Language :: Python :: 3
Classifier: Programming Language :: Python :: 3.4
Classifier: Programming Language :: Python :: 3.5
Classifier: Programming Language :: Python :: 3.6
Classifier: Programming Language :: Python :: 3.7
Classifier: Programming Language :: Python :: 3.8
Classifier: Programming Language :: Python :: 3.9
Requires-Dist: opencensus (<1.0.0,>=0.7.13)
Requires-Dist: opencensus-ext-grpc (<1.0.0,>=0.3.0)
Requires-Dist: opencensus-ext-requests (<1.0.0,>=0.1.2)
Requires-Dist: google-cloud-core (~=1.7) ; python_version == "2.7" or python_version >= "3.6"
Requires-Dist: google-cloud-core (~=1.4) ; python_version == "3.4" or python_version == "3.5"
